{
	"name": "9_E Baca Sukat 3-za_c",
	"events": [
		{
			"eventType": "block",
			"conditions": [
				{
					"id": "on-start-of-layout",
					"objectClass": "System",
					"sid": 589602002366092
				}
			],
			"actions": [
				{
					"id": "set-instvar-value",
					"objectClass": "ButtonHijau_Home1",
					"sid": 504440089927786,
					"parameters": {
						"instance-variable": "UkuranX",
						"value": "Self.Width"
					}
				},
				{
					"id": "set-instvar-value",
					"objectClass": "ButtonHijau_Home1",
					"sid": 920589384183403,
					"parameters": {
						"instance-variable": "UkuranY",
						"value": "Self.Height"
					}
				}
			],
			"sid": 732606771408984
		},
		{
			"eventType": "block",
			"conditions": [
				{
					"id": "on-touched-object",
					"objectClass": "Touch",
					"sid": 878410982118344,
					"parameters": {
						"object": "ButtonHijau_Home1"
					}
				}
			],
			"actions": [
				{
					"id": "tween-two-properties",
					"objectClass": "ButtonHijau_Home1",
					"sid": 295429177308175,
					"behaviorType": "Tween",
					"parameters": {
						"tags": "\"\"",
						"property": "size",
						"end-x": "Self.UkuranX +30",
						"end-y": "Self.UkuranY +30",
						"time": "0.1",
						"ease": "easeoutback",
						"destroy-on-complete": "no",
						"loop": "no",
						"ping-pong": "yes",
						"repeat-count": "1"
					}
				}
			],
			"sid": 694429117601011
		},
		{
			"eventType": "block",
			"conditions": [
				{
					"id": "on-start-of-layout",
					"objectClass": "System",
					"sid": 239668433175734
				}
			],
			"actions": [
				{
					"id": "set-visible",
					"objectClass": "JariPointer",
					"sid": 515309567369936,
					"parameters": {
						"visibility": "visible"
					}
				},
				{
					"id": "set-x",
					"objectClass": "JariPointer",
					"sid": 644833060803885,
					"parameters": {
						"x": "585"
					}
				}
			],
			"sid": 146280260818159
		},
		{
			"eventType": "block",
			"conditions": [
				{
					"id": "on-touched-object",
					"objectClass": "Touch",
					"sid": 641834480603301,
					"parameters": {
						"object": "Button_Maju1"
					}
				},
				{
					"id": "is-visible",
					"objectClass": "Button_Maju1",
					"sid": 730969850557704
				}
			],
			"actions": [
				{
					"id": "go-to-layout",
					"objectClass": "System",
					"sid": 687264320461408,
					"parameters": {
						"layout": "9_Baca Sukat 3-za_d"
					}
				},
				{
					"id": "play",
					"objectClass": "Audio",
					"sid": 506308275937667,
					"parameters": {
						"audio-file": "Correct Sound",
						"loop": "not-looping",
						"volume": "0",
						"stereo-pan": "0",
						"tag-optional": "\"\""
					}
				}
			],
			"sid": 340840989087148
		},
		{
			"eventType": "block",
			"conditions": [
				{
					"id": "on-touched-object",
					"objectClass": "Touch",
					"sid": 462402928219023,
					"parameters": {
						"object": "Button_Mundur1"
					}
				},
				{
					"id": "is-visible",
					"objectClass": "Button_Mundur1",
					"sid": 333632996658265
				}
			],
			"actions": [
				{
					"id": "go-to-layout",
					"objectClass": "System",
					"sid": 503800403498920,
					"parameters": {
						"layout": "9_Baca Sukat 3-za_b"
					}
				},
				{
					"id": "play",
					"objectClass": "Audio",
					"sid": 341987942422295,
					"parameters": {
						"audio-file": "negative_beeps-6008",
						"loop": "not-looping",
						"volume": "0",
						"stereo-pan": "0",
						"tag-optional": "\"\""
					}
				}
			],
			"sid": 484273648988017
		}
	],
	"sid": 934873646393679
}